amp_sdk/__init__.py
amp_sdk/core.py
amp_sdk/exceptions.py
amp_sdk/types.py
amp_sdk/py.typed
the_orb_is_awake-0.1.0.dist-info/METADATA
the_orb_is_awake-0.1.0.dist-info/WHEEL
the_orb_is_awake-0.1.0.dist-info/entry_points.txt
the_orb_is_awake-0.1.0.dist-info/licenses/LICENSE.md
the_orb_is_awake-0.1.0.dist-info/RECORD
